{
  "url": "https://salesmate.technobraingroup.com/salesmate_aws_s3/240/testimonials-public_finance_management/pdf/Elidz%20AX%20GIS%20Sharepoint%20Epm%20Testimonial%20South%20Africa",
  "title": "Elidz%20AX%20GIS%20Sharepoint%20Epm%20Testimonial%20South%20Africa",
  "content": " \n \nPage 1 of 1 \n \nReference No:  \nATTENTION:   To whom it may concern  \nFROM:    Mr M.  Nontshinga  \nICT Manager  - East London Industrial Development Zone SOC (Ltd)  \nSUBJECT:   Recommendation Letter  \nDATE:    04 May  2016  \n \nTo whom it may concern  \n \nRECOMMENDATION LETTER  \n \nThis is to certify that Techno  Brain  has successfully implemented an Enterprise Resource Management System  that consisted \nof the following integration:  \n \nDynamics AX  - this ERP was implemented to help automate the required operations within ELIDZ and also act as a base for \nfuture and any related automation needs. The following modules were installed:  Financial Management, Procurement and \nSourcing, Inventory and warehouse  management, Sales and Marketing, Facilities & Service Management, Project \nManagement and Accounting, Compliance and Audit, Microsoft Dynamics Enterprise Portal and Human Capital management  \n \nGIS - Techno Brain implemented a GIS -centric Asset Management Sys tem to improve the asset visibility, tracking and control \nfor ELIDZ’s asset base. The following modules were implemented: Property/ Building Management, Asset Management \nSystem, SCADA Integration and The Systems Administration.  \n \nMicrosoft Dynamics  CRM  - Techno Brain implemented CRM for point -and-click configurability, enterprise scalability, and easy \ninteroperability to existing applications and databases; with the following modules: Sales force and marketing automation, \nService Contracts, Lead and opportun ity management, Case management, Sales Order Management and Workflows.  \n \nMicrosoft SharePoint  - Techno Brain implemented the configuration of seven (7) sites, Configuration of portals, Upgrade and \nMigration of data from old install (limited data).  \n \nEnterpri se Performance Management  - Techno Brain implemented the EPM Suite which enabled ELIDZ to create and maintain \na culture of performance through managing metrics, scorecards, dashboards, initiatives, and plans. The following were the \nbenefits ELIDZ derived: Strategy Execution, Automation, Alignment, and Performance Evaluation.  \n \nELIDZ is  happy to confirm the application is running successfully and we are satisfied with Techno Brain’s technical expertise \nand their commitment to adher e to high standards, deliver y in time, ability to train and provide support to our staff.  ELIDZ \nappreciates  the commitment shown by Techno Brain and will continued partner with the organization on future initiatives.  \n \nFor and on Behalf of  \nEast London Industrial Development Zone SOC L td \n \n \n \n \n ",
  "hash": "660628b8ff7bc203d8a4fa3488a27c7b",
  "last_crawled": "2026-06-10T13:48:28Z",
  "last_updated": "2026-06-10T13:48:28Z"
}